Metadata-Version: 2.1
Name: pyposolver
Version: 0.2
Summary: A Python library for mathematical and physics calculations.
Home-page: https://github.com/prakhardoneria/pyposolver-prod
Author: Prakhar Doneria
Author-email: prakhardoneria3@gmail.com
Classifier: Programming Language :: Python :: 3
Classifier: License :: OSI Approved :: MIT License
Classifier: Operating System :: OS Independent
Requires-Dist: numpy
